extviews/__init__.py
extviews/connections.py
extviews/crudset.py
extviews/depends.py
extviews/exceptions.py
extviews/viewset.py
fastapi_extviews-0.1.5.dist-info/LICENSE
fastapi_extviews-0.1.5.dist-info/WHEEL
fastapi_extviews-0.1.5.dist-info/METADATA
fastapi_extviews-0.1.5.dist-info/RECORD
